riskhub/__init__.py
riskhub/riskhub.py
riskhub_sabarish-0.1.dist-info/METADATA
riskhub_sabarish-0.1.dist-info/WHEEL
riskhub_sabarish-0.1.dist-info/top_level.txt
riskhub_sabarish-0.1.dist-info/RECORD
