Metadata-Version: 2.1
Name: riskhub-sabarish
Version: 0.1
Summary: fetching URLs to any domains
Author: sabarish
Author-email: sabarishbugbounty@gmail.com
Requires-Dist: requests (==2.27.1)
Requires-Dist: argparse (==1.4.0)
Requires-Dist: apscheduler (==3.9.1)
Requires-Dist: pause (==0.3)
Requires-Dist: urllib3 (==1.24.2)
Requires-Dist: multiprocessing
